setup.cfg
setup.py
glacier_length/__init__.py
glacier_length/_src.py
glacier_length/exceptions.py
glacier_length.egg-info/PKG-INFO
glacier_length.egg-info/SOURCES.txt
glacier_length.egg-info/dependency_links.txt
glacier_length.egg-info/requires.txt
glacier_length.egg-info/top_level.txt
test/test000.py
test/test_module.py