Metadata-Version: 1.1
Name: glacier-length
Version: 1.1
Summary: extract centerline from glacier
Home-page:  
Author: Nullaha
Author-email: swdyihehe@qq.com
License:  
Platform: UNKNOWN
Classifier: Development Status :: 3 - Alpha
Classifier: Intended Audience :: Science/Research
Classifier: Topic :: Scientific/Engineering :: GIS
Classifier: License :: OSI Approved :: MIT License
Classifier: Programming Language :: Python :: 3.7
